Animate/Animate.py
Animate/Constants.py
Animate/DirectoryList.py
Animate/Frames.py
Animate/Items.py
Animate/Properties.py
Animate/Scripts.py
Animate/__init__.py
py_animate-1.0.7.dist-info/LICENSE
py_animate-1.0.7.dist-info/METADATA
py_animate-1.0.7.dist-info/WHEEL
py_animate-1.0.7.dist-info/top_level.txt
py_animate-1.0.7.dist-info/RECORD
